reqrest/__init__.py
reqrest/reqrest.py
reqrest-1.0.1.dist-info/LICENSE
reqrest-1.0.1.dist-info/METADATA
reqrest-1.0.1.dist-info/WHEEL
reqrest-1.0.1.dist-info/top_level.txt
reqrest-1.0.1.dist-info/RECORD
