Metadata-Version: 2.1
Name: reqrest
Version: 1.0.1
Summary: A REST API wrapper for requests
Home-page: https://github.com/rorymurdock/reqrest
Author: Rory Murdock
Author-email: rory@itmatic.com.au
License: UNKNOWN
Platform: UNKNOWN
Classifier: Development Status :: 5 - Production/Stable
Classifier: Programming Language :: Python :: 3
Classifier: License :: OSI Approved :: Apache Software License
Classifier: Operating System :: OS Independent
License-File: LICENSE
Requires-Dist: requests
